{
  "unevaluatedProperties" : false,
  "properties" : {
    "workOrderNumber" : {
      "title" : "workOrderNumber",
      "description" : "The Work Order number for the installation job.",
      "lightning:type" : "lightning__textType",
      "lightning:isPII" : false,
      "copilotAction:isDisplayable" : true,
      "copilotAction:isUsedByPlanner" : true
    },
    "workOrderId" : {
      "title" : "workOrderId",
      "description" : "The Salesforce ID of the Work Order record.",
      "lightning:type" : "lightning__textType",
      "lightning:isPII" : false,
      "copilotAction:isDisplayable" : true,
      "copilotAction:isUsedByPlanner" : true
    },
    "serviceAppointmentId" : {
      "title" : "serviceAppointmentId",
      "description" : "The Salesforce ID of the Service Appointment created for the installer.",
      "lightning:type" : "lightning__textType",
      "lightning:isPII" : false,
      "copilotAction:isDisplayable" : true,
      "copilotAction:isUsedByPlanner" : true
    },
    "confirmationMessage" : {
      "title" : "confirmationMessage",
      "description" : "A confirmation message with the work order details and scheduled preferences.",
      "lightning:type" : "lightning__textType",
      "lightning:isPII" : false,
      "copilotAction:isDisplayable" : true,
      "copilotAction:isUsedByPlanner" : true
    },
    "success" : {
      "title" : "success",
      "description" : "Indicates whether the work order was created/updated successfully.",
      "lightning:type" : "lightning__booleanType",
      "lightning:isPII" : false,
      "copilotAction:isDisplayable" : true,
      "copilotAction:isUsedByPlanner" : true
    }
  },
  "lightning:type" : "lightning__objectType"
}